{
    "parent": "minecraft:recipes/root",
    "rewards": {
      "recipes": [
        "archeology:raw_clay_pot"
      ]
    },
    "criteria": {
      "has_clay_ball": {
        "trigger": "minecraft:inventory_changed",
        "conditions": {
          "items": [
            {
              "items": [
                "minecraft:clay_ball"
              ]
            }
          ]
        }
      },
      "has_the_recipe": {
        "trigger": "minecraft:recipe_unlocked",
        "conditions": {
          "recipe": "archeology:raw_clay_pot"
        }
      }
    },
    "requirements": [
      [
        "has_clay_ball",
        "has_the_recipe"
      ]
    ]
  }